{
  "registry": "linux-mx-kde",
  "generatedAt": "2026-06-14T17:32:48.008Z",
  "gateA": {
    "assetsTotal": 4,
    "presentInRepo": 3,
    "missingInRepo": 0,
    "sourceTraceFile": "usr/share/capsuleos/assets/images/vendors/mx/SOURCE-VM.txt",
    "sourceTracePresent": true
  },
  "gateS": {
    "vmInventoryPath": "root/docs/inventaires/linux-mx-kde-gnome-settings-assets.json",
    "vmInventoryPresent": false,
    "sha256Compared": 0,
    "sha256Drift": 0
  },
  "missingAssets": [],
  "pullHint": "root/tools/lab/pull-vm-assets.sh"
}
