{
  "registryId": "linux-mint",
  "campaign": "v2-deep-pass",
  "vm": {
    "host": "capsule@192.168.1.146",
    "inventory": "linux-mint-vm.json",
    "labConfig": "etc/capsuleos/lab-inventory.json"
  },
  "catalog": {
    "vmMenuEntries": 101,
    "capsuleSlots": 45,
    "slotsOpenOk": 101,
    "interactionParityMeasured": true
  },
  "parity": {
    "index": "linux-mint-parity-index.json",
    "doc": "linux-mint-parity-index.md",
    "matrix": "linux-mint-ui-state-effects-matrix.json"
  },
  "priorityQueue": [
    "nemo",
    "firefox",
    "text_editor",
    "calculator",
    "file_roller",
    "update_manager",
    "mintinstall",
    "themes"
  ],
  "tools": {
    "collect": "usr/lib/capsuleos/tools/lab/collect-app-interaction-inventory.mjs",
    "parityPass": "usr/lib/capsuleos/tools/lab/run-app-parity-pass.mjs",
    "uiEffects": "usr/lib/capsuleos/tools/lab/run-ui-state-effects-pass.mjs",
    "extendMatrix": "usr/lib/capsuleos/tools/lab/extend-ui-state-effects-matrix.mjs",
    "compareVm": "usr/lib/capsuleos/tools/lab/compare-os-parity.mjs"
  },
  "pallier": 8,
  "pallier1Commit": "00816fb",
  "pallier2Commit": "aa466ab",
  "pallier3Commit": "aa71cce",
  "pallier4Commit": "37cf71f",
  "pallier5Commit": "39d115b",
  "pallier6Commit": "9a547e1",
  "pallier7Commit": "fc7396e",
  "updatedAt": "2026-06-08T14:15:00.000Z",
  "integralPass": {
    "date": "2026-06-08",
    "doc": "root/docs/recette-clone-mint-integral.md",
    "conformityReport": "root/docs/inventaires/linux-mint-clone-conformity-report.md",
    "cloisonnementScore": 94,
    "panelChecklist": "6/6",
    "vmParity": "6/6",
    "shellGeometryMaxDeltaPx": 0.7,
    "uiStateSurfaces": "8/8",
    "validateAll": "ok",
    "toolkitParadigmAll": "ok",
    "manifestDriftPull": 0,
    "manifestDriftRefs": 68
  },
  "paritySnapshot": {
    "pi_global": 98,
    "status_global": "ok",
    "priorityApps": {
      "nemo": 100,
      "firefox": 100,
      "text_editor": 92,
      "calculator": 100,
      "file_roller": 92,
      "update_manager": 100,
      "mintinstall": 100,
      "themes": 100
    },
    "shell": {
      "mainMenu": 92,
      "panel": 100,
      "tray": 100,
      "desktop": 92,
      "clock": 100,
      "theme": 100,
      "altTab": 100,
      "windowChrome": 100
    }
  },
  "nonConformites": [
    {
      "id": "MAN-DRIFT-68",
      "severity": "P2",
      "summary": "68 rewrite-ref ManΣ (icônes GTK → gnome/apps) — pull=0"
    },
    {
      "id": "CAPS-ONLY-2",
      "severity": "CapsuleOnly",
      "summary": "librewriter + checklist panel — pédagogie hors VM"
    },
    {
      "id": "MENU-CTX-50",
      "severity": "P2",
      "summary": "mainMenu ctx Π=50 — menus contextuels apps secondaires"
    }
  ],
  "notes": [
    "Pallier 8 — recette intégrale re-exécutée : VM seule vérité, smokes viewport 1280×800, altTab/windowChrome Π=100.",
    "101/101 catalogue : slots ouverts OK.",
    "Π_global 98 — 0 slot < 90.",
    "ManΣ pull=0 ; drift refs 68 documenté (apps GNOME upstream sur Mint)."
  ]
}
