{
  "registryId": "linux-mint",
  "campaignId": "mint-v2-exact-vm",
  "startedAt": "2026-06-08T08:20:09Z",
  "updatedAt": "2026-06-08T18:45:00Z",
  "scope": {
    "definition": "Réplique exacte de la VM modèle (ground truth unique) — capsule@192.168.1.146, Cinnamon 6.6.7, Mint 22.3 Zena.",
    "groundTruth": "root/docs/inventaires/linux-mint-vm.json",
    "labInventory": "etc/capsuleos/lab-inventory.json",
    "costEstimate": "root/docs/inventaires/linux-mint-replication-cost-estimate.md",
    "rules": [
      "Tout élément présent sur la VM doit exister dans Capsule avec le même rôle (objet modale Σ(S), transitions δ, effets E(δ)).",
      "CapsuleOnly interdit en clôture (checklist, retour accueil, lanceurs panel fictifs, etc.).",
      "P1 « assumé » = dette temporaire ; clôture uniquement si D=0 sur l'inventaire VM.",
      "Assets : pull VM uniquement (ManΣ), pas d'emprunt cross-vendor."
    ]
  },
  "vmSnapshot": {
    "collectedAt": "2026-06-08T10:56:00Z",
    "os": "Linux Mint 22.3 Zena",
    "cinnamon": "6.6.7",
    "nemo": "6.6.3",
    "firefox": "151.0.1",
    "theme": "Mint-Y-Dark-Aqua",
    "icons": "Mint-Y-Sand",
    "panelApplets": 15,
    "panelLaunchers": ["menu", "grouped-window-list"],
    "trayApplets": 12,
    "desktopFiles": 143,
    "menuVisibleApps": 101,
    "favoritesDesktop": 5
  },
  "metrics": {
    "appsCatalog": {
      "total": 101,
      "ok": 87,
      "partiel": 0,
      "absent": 14,
      "coverageOkPct": 86,
      "standaloneSlotsOk": 38
    },
    "surfaceVm": {
      "panelMenuFavorisTray": 17,
      "ok": 17,
      "partiel": 0
    },
    "panelChecklistVm": "6/6",
    "panelChecklistCapsule": "6/6",
    "manifestDrift": 0,
    "validateAllH2": true,
    "panelModel": "menu + grouped-window-list (2026-06-08)"
  },
  "palliers": [
    {
      "id": "P0",
      "label": "Vérité machine & inventaire",
      "predicates": ["H2", "M", "I", "ManΣ"],
      "status": "completed",
      "commit": "c3a3a00"
    },
    {
      "id": "P1",
      "label": "Shell Cinnamon (panel, WM, tray, bureau)",
      "predicates": ["Ve-shell", "Vμ-shell", "L-panel"],
      "status": "completed",
      "commit": "9cbcb8b"
    },
    {
      "id": "P2",
      "label": "Objets modaux (menus, popovers, modales)",
      "predicates": ["Va", "Ve", "Vm", "Vμ", "VΣ"],
      "status": "in_progress",
      "artifact": "linux-mint-ui-state-effects-matrix.json",
      "notes": "capsuleMatch partial sur 8 surfaces shell"
    },
    {
      "id": "P3",
      "label": "Apps VM — surface visible (panel, favoris, menu P0)",
      "predicates": ["AppΣ"],
      "status": "completed",
      "target": "17 surfaces VM → statut ok + smoke",
      "notes": "17/17 — xviewer + xreader clôturés (2026-06-08)",
      "commit": "fb0c4ef"
    },
    {
      "id": "P4",
      "label": "Apps VM — catalogue complet (101 entrées menu)",
      "predicates": ["AppΣ-full"],
      "status": "in_progress",
      "target": "101/101 slots ou équivalent VM documenté",
      "notes": "87/101 ok · batch P4 #32-39 (8 apps) + csPanel Cinnamon · 38 slots autonomes",
      "commit": "pending"
    },
    {
      "id": "P5",
      "label": "Clôture réplique intégrale",
      "predicates": ["D", "VΣ", "Tf", "H6"],
      "status": "in_progress",
      "target": "drift P0 = 0, CapsuleOnly = 0, validate-all vert",
      "notes": "manifestDrift 0 (64 refs index.html) · VΣ/H6 restants",
    }
  ],
  "predicates": {
    "H2": { "ok": true, "note": "validate-all vert" },
    "M": { "ok": true, "verifiedAt": "2026-06-08T10:56:00Z" },
    "I": { "ok": true, "file": "linux-mint-vm.json" },
    "ManΣ": { "ok": true, "lastPass": "integration-pass-2026-06-08.json" },
    "L-panel": { "ok": true, "vm": "6/6", "capsule": "6/6" },
    "AppΣ": { "ok": true, "surfaceOk": "17/17" },
    "AppΣ-full": { "ok": false, "ok": "87/101", "standaloneSlots": "38/101" },
    "VΣ": { "ok": false, "matrix": "partial" },
    "D": { "ok": true, "drift": 0, "note": "#mint-manifest-asset-refs — 64 chemins ManΣ" }
  },
  "gapClasses": {
    "retiredForClosure": ["CapsuleOnly", "P1-assumed-permanent"],
    "activeP0": [
      "14 apps catalogue absentes sur 101 (GIMP, Inkscape, mintstick, …)",
      "Matrice VΣ shell — capsuleMatch partial"
    ]
  },
  "nextActions": [
    "P4 : 14 apps restantes (GIMP, Inkscape, USB Image Writer, …)",
    "P2 : affiner VΣ capsuleMatch ok",
    "P5 : H6 clôture après AppΣ-full"
  ]
}
