{
  "version": 1,
  "registryId": "linux-rocky",
  "collectedAt": "2026-06-09T00:19:19.110Z",
  "entryCount": 85,
  "entries": [
    {
      "id": "gnome-subman-panel",
      "normalizedId": "gnome-subman-panel",
      "name": "Abonnement",
      "icon": "key-symbolic",
      "categories": "GNOME;GTK;Settings;X-GNOME-Settings-Panel;X-GNOME-SystemSettings;",
      "desktopPath": "/usr/share/applications/gnome-subman-panel.desktop",
      "origin": "system",
      "showInGrid": false,
      "hideReasons": [
        "no-display"
      ]
    },
    {
      "id": "gnome-universal-access-panel",
      "normalizedId": "gnome-universal-access-panel",
      "name": "Accessibilité",
      "icon": "org.gnome.Settings-accessibility-symbolic",
      "categories": "GNOME;GTK;Settings;X-GNOME-Settings-Panel;X-GNOME-DetailsSettings;",
      "desktopPath": "/usr/share/applications/gnome-universal-access-panel.desktop",
      "origin": "system",
      "showInGrid": false,
      "hideReasons": [
        "no-display"
      ]
    },
    {
      "id": "gcr-viewer",
      "normalizedId": "gcr-viewer",
      "name": "Afficher le fichier",
      "icon": null,
      "categories": null,
      "desktopPath": "/usr/share/applications/gcr-viewer.desktop",
      "origin": "system",
      "showInGrid": false,
      "hideReasons": [
        "no-display"
      ]
    },
    {
      "id": "org.gnome.baobab",
      "normalizedId": "org.gnome.baobab",
      "name": "Analyseur d’utilisation des disques",
      "icon": "org.gnome.baobab",
      "categories": "GTK;GNOME;System;Filesystem;X-GNOME-Utilities;",
      "desktopPath": "/usr/share/applications/org.gnome.baobab.desktop",
      "origin": "system",
      "showInGrid": true,
      "hideReasons": []
    },
    {
      "id": "org.gnome.Papers-previewer",
      "normalizedId": "org.gnome.Papers-previewer",
      "name": "Aperçu avant impression",
      "icon": "document-print-preview",
      "categories": "GNOME;GTK;Office;Viewer;Graphics;2DGraphics;VectorGraphics;",
      "desktopPath": "/usr/share/applications/org.gnome.Papers-previewer.desktop",
      "origin": "system",
      "showInGrid": false,
      "hideReasons": [
        "no-display"
      ]
    },
    {
      "id": "gnome-background-panel",
      "normalizedId": "gnome-background-panel",
      "name": "Apparence",
      "icon": "org.gnome.Settings-appearance-symbolic",
      "categories": "GNOME;GTK;Settings;DesktopSettings;X-GNOME-Settings-Panel;X-GNOME-PersonalizationSettings;",
      "desktopPath": "/usr/share/applications/gnome-background-panel.desktop",
      "origin": "system",
      "showInGrid": false,
      "hideReasons": [
        "no-display"
      ]
    },
    {
      "id": "gnome-applications-panel",
      "normalizedId": "gnome-applications-panel",
      "name": "Applications",
      "icon": "org.gnome.Settings-applications-symbolic",
      "categories": "GNOME;GTK;Settings;DesktopSettings;X-GNOME-Settings-Panel;X-GNOME-AccountSettings;",
      "desktopPath": "/usr/share/applications/gnome-applications-panel.desktop",
      "origin": "system",
      "showInGrid": false,
      "hideReasons": [
        "no-display"
      ]
    },
    {
      "id": "gnome-bluetooth-panel",
      "normalizedId": "gnome-bluetooth-panel",
      "name": "Bluetooth",
      "icon": "org.gnome.Settings-bluetooth-symbolic",
      "categories": "GTK;GNOME;Settings;X-GNOME-NetworkSettings;HardwareSettings;X-GNOME-Settings-Panel;X-GNOME-ConnectivitySettings;",
      "desktopPath": "/usr/share/applications/gnome-bluetooth-panel.desktop",
      "origin": "system",
      "showInGrid": false,
      "hideReasons": [
        "no-display"
      ]
    },
    {
      "id": "org.gnome.Calculator",
      "normalizedId": "org.gnome.Calculator",
      "name": "Calculatrice",
      "icon": "org.gnome.Calculator",
      "categories": "GNOME;GTK;Utility;Calculator;",
      "desktopPath": "/usr/share/applications/org.gnome.Calculator.desktop",
      "origin": "system",
      "showInGrid": true,
      "hideReasons": []
    },
    {
      "id": "org.gnome.Snapshot",
      "normalizedId": "org.gnome.Snapshot",
      "name": "Caméra",
      "icon": "org.gnome.Snapshot",
      "categories": "AudioVideo;Video;Recorder;GNOME;GTK;",
      "desktopPath": "/usr/share/applications/org.gnome.Snapshot.desktop",
      "origin": "system",
      "showInGrid": true,
      "hideReasons": []
    },
    {
      "id": "org.gnome.Characters",
      "normalizedId": "org.gnome.Characters",
      "name": "Caractères",
      "icon": "org.gnome.Characters",
      "categories": "GNOME;GTK;Utility;X-GNOME-Utilities;",
      "desktopPath": "/usr/share/applications/org.gnome.Characters.desktop",
      "origin": "system",
      "showInGrid": true,
      "hideReasons": []
    },
    {
      "id": "org.freedesktop.IBus.Panel.Emojier",
      "normalizedId": "org.freedesktop.IBus.Panel.Emojier",
      "name": "Choix d’émoticônes",
      "icon": "ibus",
      "categories": null,
      "desktopPath": "/usr/share/applications/org.freedesktop.IBus.Panel.Emojier.desktop",
      "origin": "system",
      "showInGrid": false,
      "hideReasons": [
        "no-display"
      ]
    },
    {
      "id": "org.freedesktop.IBus.Panel.Extension.Gtk3",
      "normalizedId": "org.freedesktop.IBus.Panel.Extension.Gtk3",
      "name": "Choix d’émoticônes",
      "icon": "ibus",
      "categories": null,
      "desktopPath": "/usr/share/applications/org.freedesktop.IBus.Panel.Extension.Gtk3.desktop",
      "origin": "system",
      "showInGrid": false,
      "hideReasons": [
        "no-display"
      ]
    },
    {
      "id": "gnome-keyboard-panel",
      "normalizedId": "gnome-keyboard-panel",
      "name": "Clavier",
      "icon": "org.gnome.Settings-keyboard-symbolic",
      "categories": "GNOME;GTK;Settings;HardwareSettings;X-GNOME-Settings-Panel;X-GNOME-DevicesSettings;",
      "desktopPath": "/usr/share/applications/gnome-keyboard-panel.desktop",
      "origin": "system",
      "showInGrid": false,
      "hideReasons": [
        "no-display"
      ]
    },
    {
      "id": "gnome-online-accounts-panel",
      "normalizedId": "gnome-online-accounts-panel",
      "name": "Comptes en ligne",
      "icon": "org.gnome.Settings-online-accounts-symbolic",
      "categories": "GNOME;GTK;Settings;DesktopSettings;X-GNOME-Settings-Panel;X-GNOME-AccountSettings;",
      "desktopPath": "/usr/share/applications/gnome-online-accounts-panel.desktop",
      "origin": "system",
      "showInGrid": false,
      "hideReasons": [
        "no-display"
      ]
    },
    {
      "id": "ibus-setup-anthy",
      "normalizedId": "ibus-setup-anthy",
      "name": "Configuration d’IBus Anthy",
      "icon": "ibus-anthy",
      "categories": null,
      "desktopPath": "/usr/share/applications/ibus-setup-anthy.desktop",
      "origin": "system",
      "showInGrid": false,
      "hideReasons": [
        "no-display"
      ]
    },
    {
      "id": "ibus-setup-m17n",
      "normalizedId": "ibus-setup-m17n",
      "name": "Configuration d’IBus M17N",
      "icon": null,
      "categories": null,
      "desktopPath": "/usr/share/applications/ibus-setup-m17n.desktop",
      "origin": "system",
      "showInGrid": false,
      "hideReasons": [
        "no-display"
      ]
    },
    {
      "id": "gnome-initial-setup",
      "normalizedId": "gnome-initial-setup",
      "name": "Configuration initiale",
      "icon": "preferences-system",
      "categories": "GNOME;GTK;System;",
      "desktopPath": "/usr/share/applications/gnome-initial-setup.desktop",
      "origin": "system",
      "showInGrid": false,
      "hideReasons": [
        "no-display"
      ]
    },
    {
      "id": "gnome-color-panel",
      "normalizedId": "gnome-color-panel",
      "name": "Couleur",
      "icon": "org.gnome.Settings-color-symbolic",
      "categories": "GNOME;GTK;Settings;X-GNOME-Settings-Panel;HardwareSettings;X-GNOME-DevicesSettings;",
      "desktopPath": "/usr/share/applications/gnome-color-panel.desktop",
      "origin": "system",
      "showInGrid": false,
      "hideReasons": [
        "no-display"
      ]
    },
    {
      "id": "gnome-datetime-panel",
      "normalizedId": "gnome-datetime-panel",
      "name": "Date et heure",
      "icon": "org.gnome.Settings-time-symbolic",
      "categories": "GNOME;GTK;Settings;X-GNOME-Settings-Panel;X-GNOME-SystemSettings;",
      "desktopPath": "/usr/share/applications/gnome-datetime-panel.desktop",
      "origin": "system",
      "showInGrid": false,
      "hideReasons": [
        "no-display"
      ]
    },
    {
      "id": "org.gnome.DiskUtility",
      "normalizedId": "org.gnome.DiskUtility",
      "name": "Disques",
      "icon": "org.gnome.DiskUtility",
      "categories": "GNOME;GTK;Utility;X-GNOME-Utilities;",
      "desktopPath": "/usr/share/applications/org.gnome.DiskUtility.desktop",
      "origin": "system",
      "showInGrid": true,
      "hideReasons": []
    },
    {
      "id": "gnome-disk-image-writer",
      "normalizedId": "gnome-disk-image-writer",
      "name": "Enregistreur d’images disque",
      "icon": "drive-removable-media",
      "categories": null,
      "desktopPath": "/usr/share/applications/gnome-disk-image-writer.desktop",
      "origin": "system",
      "showInGrid": false,
      "hideReasons": [
        "no-display"
      ]
    },
    {
      "id": "org.gnome.evolution-data-server.OAuth2-handler",
      "normalizedId": "org.gnome.evolution-data-server.OAuth2-handler",
      "name": "Evolution Data Server OAuth2 Handler",
      "icon": null,
      "categories": null,
      "desktopPath": "/usr/share/applications/org.gnome.evolution-data-server.OAuth2-handler.desktop",
      "origin": "system",
      "showInGrid": false,
      "hideReasons": [
        "no-display"
      ]
    },
    {
      "id": "org.gnome.Shell.Extensions",
      "normalizedId": "org.gnome.Shell.Extensions",
      "name": "Extensions",
      "icon": "org.gnome.Shell.Extensions",
      "categories": null,
      "desktopPath": "/usr/share/applications/org.gnome.Shell.Extensions.desktop",
      "origin": "system",
      "showInGrid": false,
      "hideReasons": [
        "no-display"
      ]
    },
    {
      "id": "org.gnome.Nautilus",
      "normalizedId": "org.gnome.Nautilus",
      "name": "Fichiers",
      "icon": "org.gnome.Nautilus",
      "categories": "GNOME;GTK;Utility;Core;FileManager;",
      "desktopPath": "/usr/share/applications/org.gnome.Nautilus.desktop",
      "origin": "system",
      "showInGrid": true,
      "hideReasons": []
    },
    {
      "id": "firefox",
      "normalizedId": "firefox",
      "name": "Firefox",
      "icon": "firefox",
      "categories": "Network;WebBrowser;",
      "desktopPath": "/usr/share/applications/firefox.desktop",
      "origin": "system",
      "showInGrid": true,
      "hideReasons": []
    },
    {
      "id": "geoclue-demo-agent",
      "normalizedId": "geoclue-demo-agent",
      "name": "Geoclue Demo agent",
      "icon": "mark-location-symbolic",
      "categories": null,
      "desktopPath": "/usr/share/applications/geoclue-demo-agent.desktop",
      "origin": "system",
      "showInGrid": false,
      "hideReasons": [
        "no-display",
        "not-show-in"
      ]
    },
    {
      "id": "org.gnome.BrowserConnector",
      "normalizedId": "org.gnome.BrowserConnector",
      "name": "GNOME browser connector",
      "icon": "org.gnome.BrowserConnector",
      "categories": null,
      "desktopPath": "/usr/share/applications/org.gnome.BrowserConnector.desktop",
      "origin": "system",
      "showInGrid": false,
      "hideReasons": [
        "no-display"
      ]
    },
    {
      "id": "org.gnome.OnlineAccounts.OAuth2",
      "normalizedId": "org.gnome.OnlineAccounts.OAuth2",
      "name": "GNOME OAuth2 Handler",
      "icon": null,
      "categories": null,
      "desktopPath": "/usr/share/applications/org.gnome.OnlineAccounts.OAuth2.desktop",
      "origin": "system",
      "showInGrid": false,
      "hideReasons": [
        "no-display"
      ]
    },
    {
      "id": "org.gnome.RemoteDesktop.Handover",
      "normalizedId": "org.gnome.RemoteDesktop.Handover",
      "name": "GNOME Remote Desktop Handover Daemon",
      "icon": null,
      "categories": null,
      "desktopPath": "/usr/share/applications/org.gnome.RemoteDesktop.Handover.desktop",
      "origin": "system",
      "showInGrid": false,
      "hideReasons": [
        "no-display"
      ]
    },
    {
      "id": "org.gnome.Shell",
      "normalizedId": "org.gnome.Shell",
      "name": "GNOME Shell",
      "icon": null,
      "categories": "GNOME;GTK;Core;",
      "desktopPath": "/usr/share/applications/org.gnome.Shell.desktop",
      "origin": "system",
      "showInGrid": false,
      "hideReasons": [
        "no-display"
      ]
    },
    {
      "id": "org.gnome.clocks",
      "normalizedId": "org.gnome.clocks",
      "name": "Horloges",
      "icon": "org.gnome.clocks",
      "categories": "GNOME;GTK;Utility;Clock;",
      "desktopPath": "/usr/share/applications/org.gnome.clocks.desktop",
      "origin": "system",
      "showInGrid": true,
      "hideReasons": []
    },
    {
      "id": "ibus-setup-hangul",
      "normalizedId": "ibus-setup-hangul",
      "name": "IBus Hangul Preferences",
      "icon": "ibus-setup-hangul",
      "categories": "Settings;",
      "desktopPath": "/usr/share/applications/ibus-setup-hangul.desktop",
      "origin": "system",
      "showInGrid": false,
      "hideReasons": [
        "no-display"
      ]
    },
    {
      "id": "ibus-setup-libzhuyin",
      "normalizedId": "ibus-setup-libzhuyin",
      "name": "IBus LibZhuyin Setup",
      "icon": "/usr/share/ibus-libzhuyin/icons/ibus-zhuyin.svg",
      "categories": null,
      "desktopPath": "/usr/share/applications/ibus-setup-libzhuyin.desktop",
      "origin": "system",
      "showInGrid": false,
      "hideReasons": [
        "no-display"
      ]
    },
    {
      "id": "gnome-printers-panel",
      "normalizedId": "gnome-printers-panel",
      "name": "Imprimantes",
      "icon": "org.gnome.Settings-printers-symbolic",
      "categories": "GNOME;GTK;Settings;HardwareSettings;X-GNOME-Settings-Panel;X-GNOME-DevicesSettings;",
      "desktopPath": "/usr/share/applications/gnome-printers-panel.desktop",
      "origin": "system",
      "showInGrid": false,
      "hideReasons": [
        "no-display"
      ]
    },
    {
      "id": "gnome-software-local-file-flatpak",
      "normalizedId": "gnome-software-local-file-flatpak",
      "name": "Installation de l’application",
      "icon": "system-software-install",
      "categories": "System;",
      "desktopPath": "/usr/share/applications/gnome-software-local-file-flatpak.desktop",
      "origin": "system",
      "showInGrid": false,
      "hideReasons": [
        "no-display"
      ]
    },
    {
      "id": "gnome-software-local-file-fwupd",
      "normalizedId": "gnome-software-local-file-fwupd",
      "name": "Installation de l’application",
      "icon": "system-software-install",
      "categories": "System;",
      "desktopPath": "/usr/share/applications/gnome-software-local-file-fwupd.desktop",
      "origin": "system",
      "showInGrid": false,
      "hideReasons": [
        "no-display"
      ]
    },
    {
      "id": "gnome-software-local-file-packagekit",
      "normalizedId": "gnome-software-local-file-packagekit",
      "name": "Installation de l’application",
      "icon": "system-software-install",
      "categories": "System;",
      "desktopPath": "/usr/share/applications/gnome-software-local-file-packagekit.desktop",
      "origin": "system",
      "showInGrid": false,
      "hideReasons": [
        "no-display"
      ]
    },
    {
      "id": "liveinst",
      "normalizedId": "liveinst",
      "name": "Installer sur le disque dur",
      "icon": "org.fedoraproject.AnacondaInstaller",
      "categories": "System;Utility;X-Red-Hat-Base;X-Fedora;GNOME;GTK;",
      "desktopPath": "/usr/share/applications/liveinst.desktop",
      "origin": "system",
      "showInGrid": false,
      "hideReasons": [
        "no-display"
      ]
    },
    {
      "id": "gcr-prompter",
      "normalizedId": "gcr-prompter",
      "name": "Invite d’accès",
      "icon": "security-medium",
      "categories": null,
      "desktopPath": "/usr/share/applications/gcr-prompter.desktop",
      "origin": "system",
      "showInGrid": false,
      "hideReasons": [
        "no-display"
      ]
    },
    {
      "id": "setroubleshoot",
      "normalizedId": "setroubleshoot",
      "name": "Journal des alertes SELinux",
      "icon": "setroubleshoot_icon",
      "categories": "System;",
      "desktopPath": "/usr/share/applications/setroubleshoot.desktop",
      "origin": "system",
      "showInGrid": true,
      "hideReasons": []
    },
    {
      "id": "nautilus-autorun-software",
      "normalizedId": "nautilus-autorun-software",
      "name": "Lancer le logiciel",
      "icon": "application-x-executable",
      "categories": null,
      "desktopPath": "/usr/share/applications/nautilus-autorun-software.desktop",
      "origin": "system",
      "showInGrid": false,
      "hideReasons": [
        "no-display"
      ]
    },
    {
      "id": "org.gnome.Software",
      "normalizedId": "org.gnome.Software",
      "name": "Logiciels",
      "icon": "org.gnome.Software",
      "categories": "GNOME;GTK;System;PackageManager;",
      "desktopPath": "/usr/share/applications/org.gnome.Software.desktop",
      "origin": "system",
      "showInGrid": true,
      "hideReasons": []
    },
    {
      "id": "org.gnome.SystemMonitor",
      "normalizedId": "org.gnome.SystemMonitor",
      "name": "Moniteur système",
      "icon": "org.gnome.SystemMonitor",
      "categories": "GNOME;GTK;System;Monitor;",
      "desktopPath": "/usr/share/applications/org.gnome.SystemMonitor.desktop",
      "origin": "system",
      "showInGrid": true,
      "hideReasons": []
    },
    {
      "id": "gnome-system-monitor-kde",
      "normalizedId": "gnome-system-monitor-kde",
      "name": "Moniteur système de GNOME",
      "icon": "org.gnome.SystemMonitor",
      "categories": "GNOME;GTK;System;Monitor;",
      "desktopPath": "/usr/share/applications/gnome-system-monitor-kde.desktop",
      "origin": "system",
      "showInGrid": false,
      "hideReasons": [
        "only-show-in-mismatch"
      ]
    },
    {
      "id": "gnome-disk-image-mounter",
      "normalizedId": "gnome-disk-image-mounter",
      "name": "Monteur d’images disque",
      "icon": "drive-removable-media",
      "categories": null,
      "desktopPath": "/usr/share/applications/gnome-disk-image-mounter.desktop",
      "origin": "system",
      "showInGrid": false,
      "hideReasons": [
        "no-display"
      ]
    },
    {
      "id": "gnome-multitasking-panel",
      "normalizedId": "gnome-multitasking-panel",
      "name": "Multi-tâches",
      "icon": "org.gnome.Settings-multitasking-symbolic",
      "categories": "GNOME;GTK;Settings;DesktopSettings;X-GNOME-Settings-Panel;X-GNOME-PersonalizationSettings;",
      "desktopPath": "/usr/share/applications/gnome-multitasking-panel.desktop",
      "origin": "system",
      "showInGrid": false,
      "hideReasons": [
        "no-display"
      ]
    },
    {
      "id": "gnome-notifications-panel",
      "normalizedId": "gnome-notifications-panel",
      "name": "Notifications",
      "icon": "org.gnome.Settings-notifications-symbolic",
      "categories": "GNOME;GTK;Settings;DesktopSettings;X-GNOME-Settings-Panel;X-GNOME-PersonalizationSettings;",
      "desktopPath": "/usr/share/applications/gnome-notifications-panel.desktop",
      "origin": "system",
      "showInGrid": false,
      "hideReasons": [
        "no-display"
      ]
    },
    {
      "id": "org.gnome.Papers",
      "normalizedId": "org.gnome.Papers",
      "name": "Papiers",
      "icon": "org.gnome.Papers",
      "categories": "GNOME;GTK;Office;Viewer;Graphics;2DGraphics;VectorGraphics;",
      "desktopPath": "/usr/share/applications/org.gnome.Papers.desktop",
      "origin": "system",
      "showInGrid": true,
      "hideReasons": []
    },
    {
      "id": "org.gnome.Settings",
      "normalizedId": "org.gnome.Settings",
      "name": "Paramètres",
      "icon": "org.gnome.Settings",
      "categories": "GNOME;GTK;Settings;",
      "desktopPath": "/usr/share/applications/org.gnome.Settings.desktop",
      "origin": "system",
      "showInGrid": true,
      "hideReasons": []
    },
    {
      "id": "ibus-setup-libpinyin",
      "normalizedId": "ibus-setup-libpinyin",
      "name": "Paramètres de IBus LibPinyin",
      "icon": "/usr/share/ibus-libpinyin/icons/ibus-pinyin.svg",
      "categories": null,
      "desktopPath": "/usr/share/applications/ibus-setup-libpinyin.desktop",
      "origin": "system",
      "showInGrid": false,
      "hideReasons": [
        "no-display"
      ]
    },
    {
      "id": "gnome-sharing-panel",
      "normalizedId": "gnome-sharing-panel",
      "name": "Partage",
      "icon": "org.gnome.Settings-sharing-symbolic",
      "categories": "GNOME;GTK;Settings;DesktopSettings;X-GNOME-Settings-Panel;X-GNOME-AccountSettings;",
      "desktopPath": "/usr/share/applications/gnome-sharing-panel.desktop",
      "origin": "system",
      "showInGrid": false,
      "hideReasons": [
        "no-display"
      ]
    },
    {
      "id": "gnome-region-panel",
      "normalizedId": "gnome-region-panel",
      "name": "Pays et langue",
      "icon": "org.gnome.Settings-region-symbolic",
      "categories": "GNOME;GTK;Settings;DesktopSettings;X-GNOME-Settings-Panel;X-GNOME-SystemSettings;",
      "desktopPath": "/usr/share/applications/gnome-region-panel.desktop",
      "origin": "system",
      "showInGrid": false,
      "hideReasons": [
        "no-display"
      ]
    },
    {
      "id": "org.gnome.font-viewer",
      "normalizedId": "org.gnome.font-viewer",
      "name": "Polices",
      "icon": "org.gnome.font-viewer",
      "categories": "GTK;GNOME;Utility;X-GNOME-Utilities;",
      "desktopPath": "/usr/share/applications/org.gnome.font-viewer.desktop",
      "origin": "system",
      "showInGrid": true,
      "hideReasons": []
    },
    {
      "id": "xdg-desktop-portal-gnome",
      "normalizedId": "xdg-desktop-portal-gnome",
      "name": "Portail",
      "icon": "applications-system-symbolic",
      "categories": null,
      "desktopPath": "/usr/share/applications/xdg-desktop-portal-gnome.desktop",
      "origin": "system",
      "showInGrid": false,
      "hideReasons": [
        "no-display"
      ]
    },
    {
      "id": "xdg-desktop-portal-gtk",
      "normalizedId": "xdg-desktop-portal-gtk",
      "name": "Portal",
      "icon": "applications-system-symbolic",
      "categories": null,
      "desktopPath": "/usr/share/applications/xdg-desktop-portal-gtk.desktop",
      "origin": "system",
      "showInGrid": false,
      "hideReasons": [
        "no-display"
      ]
    },
    {
      "id": "gcm-import",
      "normalizedId": "gcm-import",
      "name": "Programme d’installation de profil de couleur ICC",
      "icon": "application-vnd.iccprofile",
      "categories": "System;",
      "desktopPath": "/usr/share/applications/gcm-import.desktop",
      "origin": "system",
      "showInGrid": false,
      "hideReasons": [
        "no-display"
      ]
    },
    {
      "id": "org.freedesktop.IBus.Setup",
      "normalizedId": "org.freedesktop.IBus.Setup",
      "name": "Préférences de IBus",
      "icon": "ibus-setup",
      "categories": "Settings;",
      "desktopPath": "/usr/share/applications/org.freedesktop.IBus.Setup.desktop",
      "origin": "system",
      "showInGrid": false,
      "hideReasons": [
        "no-display",
        "not-show-in"
      ]
    },
    {
      "id": "ibus-setup-libbopomofo",
      "normalizedId": "ibus-setup-libbopomofo",
      "name": "Préférences de IBus LibBopomofo",
      "icon": "/usr/share/ibus-libpinyin/icons/ibus-bopomofo.svg",
      "categories": null,
      "desktopPath": "/usr/share/applications/ibus-setup-libbopomofo.desktop",
      "origin": "system",
      "showInGrid": false,
      "hideReasons": [
        "no-display"
      ]
    },
    {
      "id": "org.gnome.Evolution-alarm-notify",
      "normalizedId": "org.gnome.Evolution-alarm-notify",
      "name": "Rappels des évènements et des tâches",
      "icon": "org.gnome.Evolution-alarm-notify",
      "categories": null,
      "desktopPath": "/usr/share/applications/org.gnome.Evolution-alarm-notify.desktop",
      "origin": "system",
      "showInGrid": false,
      "hideReasons": [
        "no-display"
      ]
    },
    {
      "id": "gnome-search-panel",
      "normalizedId": "gnome-search-panel",
      "name": "Rechercher",
      "icon": "org.gnome.Settings-search-symbolic",
      "categories": "GNOME;GTK;Settings;DesktopSettings;X-GNOME-Settings-Panel;X-GNOME-PersonalizationSettings;",
      "desktopPath": "/usr/share/applications/gnome-search-panel.desktop",
      "origin": "system",
      "showInGrid": false,
      "hideReasons": [
        "no-display"
      ]
    },
    {
      "id": "gnome-network-panel",
      "normalizedId": "gnome-network-panel",
      "name": "Réseau",
      "icon": "org.gnome.Settings-network-symbolic",
      "categories": "GNOME;GTK;Settings;HardwareSettings;X-GNOME-Settings-Panel;X-GNOME-ConnectivitySettings;",
      "desktopPath": "/usr/share/applications/gnome-network-panel.desktop",
      "origin": "system",
      "showInGrid": false,
      "hideReasons": [
        "no-display"
      ]
    },
    {
      "id": "gnome-wwan-panel",
      "normalizedId": "gnome-wwan-panel",
      "name": "Réseau mobile",
      "icon": "org.gnome.Settings-mobile-network-symbolic",
      "categories": "GNOME;GTK;Settings;X-GNOME-NetworkSettings;HardwareSettings;X-GNOME-Settings-Panel;X-GNOME-ConnectivitySettings;",
      "desktopPath": "/usr/share/applications/gnome-wwan-panel.desktop",
      "origin": "system",
      "showInGrid": false,
      "hideReasons": [
        "no-display"
      ]
    },
    {
      "id": "gnome-sound-panel",
      "normalizedId": "gnome-sound-panel",
      "name": "Son",
      "icon": "org.gnome.Settings-sound-symbolic",
      "categories": "GNOME;GTK;Settings;X-GNOME-Settings-Panel;X-GNOME-DevicesSettings;",
      "desktopPath": "/usr/share/applications/gnome-sound-panel.desktop",
      "origin": "system",
      "showInGrid": false,
      "hideReasons": [
        "no-display"
      ]
    },
    {
      "id": "gnome-mouse-panel",
      "normalizedId": "gnome-mouse-panel",
      "name": "Sou­ris et pavé tac­tile",
      "icon": "org.gnome.Settings-mouse-symbolic",
      "categories": "GNOME;GTK;Settings;HardwareSettings;X-GNOME-Settings-Panel;X-GNOME-DevicesSettings;",
      "desktopPath": "/usr/share/applications/gnome-mouse-panel.desktop",
      "origin": "system",
      "showInGrid": false,
      "hideReasons": [
        "no-display"
      ]
    },
    {
      "id": "gnome-system-panel",
      "normalizedId": "gnome-system-panel",
      "name": "Système",
      "icon": "org.gnome.Settings-system-symbolic",
      "categories": "GNOME;GTK;Settings;X-GNOME-Settings-Panel;X-GNOME-DetailsSettings;",
      "desktopPath": "/usr/share/applications/gnome-system-panel.desktop",
      "origin": "system",
      "showInGrid": false,
      "hideReasons": [
        "no-display"
      ]
    },
    {
      "id": "gcm-picker",
      "normalizedId": "gcm-picker",
      "name": "Sélecteur de couleurs",
      "icon": "gnome-color-manager",
      "categories": "GNOME;GTK;System;",
      "desktopPath": "/usr/share/applications/gcm-picker.desktop",
      "origin": "system",
      "showInGrid": false,
      "hideReasons": [
        "no-display"
      ]
    },
    {
      "id": "gnome-wacom-panel",
      "normalizedId": "gnome-wacom-panel",
      "name": "Tablette Wacom",
      "icon": "org.gnome.Settings-wacom-symbolic",
      "categories": "GNOME;GTK;Settings;HardwareSettings;X-GNOME-Settings-Panel;X-GNOME-DevicesSettings;",
      "desktopPath": "/usr/share/applications/gnome-wacom-panel.desktop",
      "origin": "system",
      "showInGrid": false,
      "hideReasons": [
        "no-display"
      ]
    },
    {
      "id": "org.gnome.Tecla",
      "normalizedId": "org.gnome.Tecla",
      "name": "Tecla",
      "icon": "org.gnome.Tecla",
      "categories": "GNOME;GTK;Core;System;",
      "desktopPath": "/usr/share/applications/org.gnome.Tecla.desktop",
      "origin": "system",
      "showInGrid": false,
      "hideReasons": [
        "no-display"
      ]
    },
    {
      "id": "org.gnome.Ptyxis",
      "normalizedId": "org.gnome.Ptyxis",
      "name": "Terminal",
      "icon": "org.gnome.Ptyxis",
      "categories": "GNOME;GTK;System;TerminalEmulator;",
      "desktopPath": "/usr/share/applications/org.gnome.Ptyxis.desktop",
      "origin": "system",
      "showInGrid": true,
      "hideReasons": []
    },
    {
      "id": "bluetooth-sendto",
      "normalizedId": "bluetooth-sendto",
      "name": "Transfert Bluetooth",
      "icon": "bluetooth",
      "categories": "GTK;GNOME;Utility;FileTools;",
      "desktopPath": "/usr/share/applications/bluetooth-sendto.desktop",
      "origin": "system",
      "showInGrid": false,
      "hideReasons": [
        "no-display"
      ]
    },
    {
      "id": "ibus-setup-typing-booster",
      "normalizedId": "ibus-setup-typing-booster",
      "name": "Typing Booster Preferences",
      "icon": "ibus-typing-booster",
      "categories": null,
      "desktopPath": "/usr/share/applications/ibus-setup-typing-booster.desktop",
      "origin": "system",
      "showInGrid": false,
      "hideReasons": [
        "no-display"
      ]
    },
    {
      "id": "gnome-users-panel",
      "normalizedId": "gnome-users-panel",
      "name": "Utilisateurs",
      "icon": "org.gnome.Settings-users-symbolic",
      "categories": "GNOME;GTK;Settings;X-GNOME-Settings-Panel;X-GNOME-SystemSettings;",
      "desktopPath": "/usr/share/applications/gnome-users-panel.desktop",
      "origin": "system",
      "showInGrid": false,
      "hideReasons": [
        "no-display"
      ]
    },
    {
      "id": "gnome-privacy-panel",
      "normalizedId": "gnome-privacy-panel",
      "name": "Vie privée et sécurité",
      "icon": "org.gnome.Settings-privacy-symbolic",
      "categories": "GNOME;GTK;Settings;DesktopSettings;X-GNOME-Settings-Panel;X-GNOME-AccountSettings;",
      "desktopPath": "/usr/share/applications/gnome-privacy-panel.desktop",
      "origin": "system",
      "showInGrid": false,
      "hideReasons": [
        "no-display"
      ]
    },
    {
      "id": "org.gnome.ColorProfileViewer",
      "normalizedId": "org.gnome.ColorProfileViewer",
      "name": "Visionneur de profil de couleurs",
      "icon": "gnome-color-manager",
      "categories": "GNOME;GTK;System;",
      "desktopPath": "/usr/share/applications/org.gnome.ColorProfileViewer.desktop",
      "origin": "system",
      "showInGrid": false,
      "hideReasons": [
        "not-show-in"
      ]
    },
    {
      "id": "org.gnome.Loupe",
      "normalizedId": "org.gnome.Loupe",
      "name": "Visionneur d’images",
      "icon": "org.gnome.Loupe",
      "categories": "GNOME;GTK;Graphics;2DGraphics;RasterGraphics;Viewer;",
      "desktopPath": "/usr/share/applications/org.gnome.Loupe.desktop",
      "origin": "system",
      "showInGrid": true,
      "hideReasons": []
    },
    {
      "id": "org.gnome.Tour",
      "normalizedId": "org.gnome.Tour",
      "name": "Visite guidée",
      "icon": "org.gnome.Tour",
      "categories": "GNOME;GTK;Documentation;Utility;",
      "desktopPath": "/usr/share/applications/org.gnome.Tour.desktop",
      "origin": "system",
      "showInGrid": true,
      "hideReasons": []
    },
    {
      "id": "gnome-wifi-panel",
      "normalizedId": "gnome-wifi-panel",
      "name": "Wi-Fi",
      "icon": "network-wireless-symbolic",
      "categories": "GNOME;GTK;Settings;HardwareSettings;X-GNOME-Settings-Panel;X-GNOME-ConnectivitySettings;",
      "desktopPath": "/usr/share/applications/gnome-wifi-panel.desktop",
      "origin": "system",
      "showInGrid": false,
      "hideReasons": [
        "no-display"
      ]
    },
    {
      "id": "org.freedesktop.Xwayland",
      "normalizedId": "org.freedesktop.Xwayland",
      "name": "Xwayland",
      "icon": null,
      "categories": "System;",
      "desktopPath": "/usr/share/applications/org.freedesktop.Xwayland.desktop",
      "origin": "system",
      "showInGrid": false,
      "hideReasons": [
        "no-display"
      ]
    },
    {
      "id": "yelp-build-url-handler",
      "normalizedId": "yelp-build-url-handler",
      "name": "Yelp URL Handler",
      "icon": null,
      "categories": null,
      "desktopPath": "/usr/share/applications/yelp-build-url-handler.desktop",
      "origin": "system",
      "showInGrid": false,
      "hideReasons": [
        "no-display"
      ]
    },
    {
      "id": "org.gnome.Zenity",
      "normalizedId": "org.gnome.Zenity",
      "name": "Zenity",
      "icon": null,
      "categories": null,
      "desktopPath": "/usr/share/applications/org.gnome.Zenity.desktop",
      "origin": "system",
      "showInGrid": false,
      "hideReasons": [
        "no-display"
      ]
    },
    {
      "id": "gnome-about-panel",
      "normalizedId": "gnome-about-panel",
      "name": "À propos",
      "icon": "org.gnome.Settings-about-symbolic",
      "categories": "GNOME;GTK;Settings;X-GNOME-Settings-Panel;X-GNOME-SystemSettings;",
      "desktopPath": "/usr/share/applications/gnome-about-panel.desktop",
      "origin": "system",
      "showInGrid": false,
      "hideReasons": [
        "no-display"
      ]
    },
    {
      "id": "gnome-display-panel",
      "normalizedId": "gnome-display-panel",
      "name": "Éc­rans",
      "icon": "org.gnome.Settings-display-symbolic",
      "categories": "GNOME;GTK;Settings;HardwareSettings;X-GNOME-Settings-Panel;X-GNOME-DevicesSettings;",
      "desktopPath": "/usr/share/applications/gnome-display-panel.desktop",
      "origin": "system",
      "showInGrid": false,
      "hideReasons": [
        "no-display"
      ]
    },
    {
      "id": "org.gnome.TextEditor",
      "normalizedId": "org.gnome.TextEditor",
      "name": "Éditeur de texte",
      "icon": "org.gnome.TextEditor",
      "categories": "GNOME;GTK;Utility;TextEditor;",
      "desktopPath": "/usr/share/applications/org.gnome.TextEditor.desktop",
      "origin": "system",
      "showInGrid": true,
      "hideReasons": []
    },
    {
      "id": "gnome-power-panel",
      "normalizedId": "gnome-power-panel",
      "name": "Énergie",
      "icon": "org.gnome.Settings-power-symbolic",
      "categories": "GNOME;GTK;Settings;DesktopSettings;X-GNOME-Settings-Panel;X-GNOME-DevicesSettings;",
      "desktopPath": "/usr/share/applications/gnome-power-panel.desktop",
      "origin": "system",
      "showInGrid": false,
      "hideReasons": [
        "no-display"
      ]
    }
  ]
}
